antiope/__init__.py
antiope/_version.py
antiope/aws_account.py
antiope/aws_organization.py
antiope/config.py
antiope/foreign_aws_account.py
antiope/vpc.py
antiope-1.2.1.dist-info/LICENSE
antiope-1.2.1.dist-info/METADATA
antiope-1.2.1.dist-info/WHEEL
antiope-1.2.1.dist-info/top_level.txt
antiope-1.2.1.dist-info/RECORD
