Metadata-Version: 2.1
Name: antiope
Version: 1.2.1
Summary: Library for interacting with AWS accounts that are tied to the Antiope framework
Home-page: https://github.com/WarnerMedia/antiope-aws-module.git
Author: Chris Farris
Author-email: chris@room17.com
License: Apache License 2.0
Platform: UNKNOWN
Requires-Python: >=3.6
License-File: LICENSE
Requires-Dist: boto3 (>=1.10.0)
Requires-Dist: botocore (>=1.13.0)
